hanzo_tools/__init__.py
hanzo_tools/config/__init__.py
hanzo_tools/config/config_tool.py
hanzo_tools/config/index_config.py
hanzo_tools/config/mode_tool.py
hanzo_tools_config-0.2.0.dist-info/METADATA
hanzo_tools_config-0.2.0.dist-info/WHEEL
hanzo_tools_config-0.2.0.dist-info/entry_points.txt
hanzo_tools_config-0.2.0.dist-info/top_level.txt
hanzo_tools_config-0.2.0.dist-info/RECORD
