Metadata-Version: 2.4
Name: hanzo-tools-config
Version: 0.2.0
Summary: Configuration tools for Hanzo AI - mode, settings management
Author-email: Hanzo Industries Inc <dev@hanzo.ai>
License: MIT
Keywords: hanzo,tools,config,mcp,ai
Requires-Python: >=3.12
Requires-Dist: hanzo-tools-core>=0.1.0
Requires-Dist: mcp>=1.25.0
Requires-Dist: fastmcp>=2.14.1
Requires-Dist: pydantic>=2.12.5
